scripts/config_value.py
scripts/git-timesync
scripts/git_update_mtime.sh
scripts/move_empty_files.sh
scripts/setup-pipeline
scripts/stanza_models.sh
scripts/wip/Makefile
scripts/wip/prepare_sparv.sh
scripts/wip/setup.sh
workflow/Makefile
workflow/README.md
workflow/Snakefile
workflow/__init__.py
workflow/config/__init__.py
workflow/config/config.yml
workflow/config/test_config.yml
workflow/config/typed_config.py
workflow/rules/__init__.py
workflow/rules/__paths__.py
workflow/rules/compute_frequency.smk
workflow/rules/extract_speeches.smk
workflow/rules/help.smk
workflow/rules/tag_protocols.smk
workflow/rules/update_repository.smk
workflow/taggers/__init__.py
workflow/taggers/registry.py
workflow/taggers/spacy2.py
workflow/taggers/stanza.py
workflow/utility.py
westac_parlaclarin_pipeline-2021.11.3.dist-info/entry_points.txt
westac_parlaclarin_pipeline-2021.11.3.dist-info/LICENSE
westac_parlaclarin_pipeline-2021.11.3.dist-info/WHEEL
westac_parlaclarin_pipeline-2021.11.3.dist-info/METADATA
westac_parlaclarin_pipeline-2021.11.3.dist-info/RECORD
