Metadata-Version: 2.1
Name: westac-parlaclarin-pipeline
Version: 2021.11.3
Summary: Pipeline that transforms Parla-Clarin XML files
Home-page: https://westac.se
License: Apache-2.0
Author: Roger Mähler
Author-email: roger.mahler@hotmail.com
Requires-Python: ==3.8.5
Classifier: License :: OSI Approved :: Apache Software License
Classifier: Operating System :: OS Independent
Classifier: Programming Language :: Python
Classifier: Programming Language :: Python :: 3
Classifier: Programming Language :: Python :: 3.8
Classifier: Topic :: Software Development
Requires-Dist: click (>=7.1.2,<8.0.0)
Requires-Dist: cookiecutter (>=1.7.2,<2.0.0)
Requires-Dist: dehyphen (>=0.3.4,<0.4.0)
Requires-Dist: loguru (>=0.5.3,<0.6.0)
Requires-Dist: pandas (>=1.2.3,<2.0.0)
Requires-Dist: pygit2 (>=1.5.0,<2.0.0)
Requires-Dist: pyriksprot (>=2021.9.8,<2022.0.0)
Requires-Dist: snakefmt (>=0.3.1,<0.4.0)
Requires-Dist: snakemake (>=6.0.5,<7.0.0)
Requires-Dist: stanza (>=1.2.3,<2.0.0)
Requires-Dist: transformers (>=4.3.3,<5.0.0)
Project-URL: Repository, https://github.com/welfare-state-analytics/westac_parlaclarin_pipeline
